{
  "id": "BIO-101-1B",
  "title": "Microscopy and Magnification",
  "description": "Use magnification to observe cells and estimate size.",
  "layout": "linear-flow",
  "unit": "Unit BIO-101",
  "topic": "Microscopy",
  "learningOutcomes": [
    "Define magnification and resolution.",
    "Use a simple magnification formula.",
    "Explain why electron microscopes show more detail."
  ],
  "prerequisites": ["BIO-101-1A"],
  "blocks": [
    {
      "id": "BIO-101-1B-outcomes",
      "type": "outcomes",
      "order": 1,
      "content": {
        "outcomes": [
          { "text": "Define magnification and resolution.", "bloomLevel": "remember" },
          { "text": "Apply magnification formula.", "bloomLevel": "apply" }
        ]
      }
    },
    {
      "id": "BIO-101-1B-explain",
      "type": "explanation",
      "order": 2,
      "content": {
        "title": "Key microscope ideas",
        "content": "Magnification = image size / actual size. Resolution is how clearly two close points can be separated. Electron microscopes have higher resolution than light microscopes."
      }
    },
    {
      "id": "BIO-101-1B-worked",
      "type": "worked-example",
      "order": 3,
      "content": {
        "title": "Magnification example",
        "given": "Image size = 20 mm, actual size = 0.02 mm",
        "steps": [
          { "stepNumber": 1, "description": "Use magnification formula.", "formula": "magnification = image / actual" },
          { "stepNumber": 2, "description": "Substitute values.", "calculation": "20 / 0.02" },
          { "stepNumber": 3, "description": "Compute answer.", "result": "1000" }
        ]
      }
    },
    {
      "id": "BIO-101-1B-practice",
      "type": "practice",
      "order": 4,
      "content": {
        "title": "Practice",
        "questions": [
          {
            "id": "BIO-101-1B-Q1",
            "questionText": "If image size is 12 mm and actual size is 0.03 mm, what is magnification?",
            "expectedAnswer": ["400", "x400", "400x"],
            "answerType": "short-text"
          },
          {
            "id": "BIO-101-1B-Q2",
            "questionText": "Why are electron microscopes useful for seeing internal cell structures?",
            "expectedAnswer": ["higher resolution", "better resolution", "greater resolving power"],
            "answerType": "short-text"
          }
        ]
      }
    },
    {
      "id": "BIO-101-1B-review",
      "type": "spaced-review",
      "order": 5,
      "content": {
        "title": "Review",
        "questions": [
          {
            "id": "BIO-101-1B-R1",
            "questionText": "State the magnification formula.",
            "expectedAnswer": ["image size divided by actual size", "magnification = image size / actual size"]
          }
        ]
      }
    }
  ],
  "metadata": {
    "created": "2026-03-08T00:00:00.000Z",
    "updated": "2026-03-08T00:00:00.000Z",
    "version": "2.0.0",
    "author": "v2-content",
    "contentVersion": 1
  }
}
